streamlit_chat/__init__.py
streamlit_chat/frontend/build/asset-manifest.json
streamlit_chat/frontend/build/bootstrap.min.css
streamlit_chat/frontend/build/bootstrap.min.css.map
streamlit_chat/frontend/build/index.html
streamlit_chat/frontend/build/precache-manifest.b07dcacca392a0fa95672bace19f7fb1.js
streamlit_chat/frontend/build/service-worker.js
streamlit_chat/frontend/build/static/js/2.82d6880e.chunk.js
streamlit_chat/frontend/build/static/js/2.82d6880e.chunk.js.LICENSE.txt
streamlit_chat/frontend/build/static/js/2.82d6880e.chunk.js.map
streamlit_chat/frontend/build/static/js/main.342b5169.chunk.js
streamlit_chat/frontend/build/static/js/main.342b5169.chunk.js.map
streamlit_chat/frontend/build/static/js/runtime-main.11ec9aca.js
streamlit_chat/frontend/build/static/js/runtime-main.11ec9aca.js.map
streamlit_chatbot-0.0.2.2.dist-info/LICENSE
streamlit_chatbot-0.0.2.2.dist-info/METADATA
streamlit_chatbot-0.0.2.2.dist-info/WHEEL
streamlit_chatbot-0.0.2.2.dist-info/top_level.txt
streamlit_chatbot-0.0.2.2.dist-info/RECORD
