Metadata-Version: 2.1
Name: streamlit-chatbot
Version: 0.0.2.2
Summary: A streamlit component, to make chatbots
Home-page: https://github.com/AI-Yash/st-chat
Author: Darin Manley
Author-email: Darin.j.manley@gmail.com
License: UNKNOWN
Keywords: chat streamlit streamlit-component
Platform: UNKNOWN
Classifier: Programming Language :: Python :: 3
Classifier: Operating System :: OS Independent
Requires-Python: >=3.8
License-File: LICENSE
